langswarm/core/__init__.py
langswarm/core/base/__init__.py
langswarm/core/base/bot.py
langswarm/core/base/log.py
langswarm/core/factory/__init__.py
langswarm/core/factory/agents.py
langswarm/core/registry/__init__.py
langswarm/core/registry/agents.py
langswarm/core/utils/__init__.py
langswarm/core/utils/utilities.py
langswarm/core/wrappers/__init__.py
langswarm/core/wrappers/base_wrapper.py
langswarm/core/wrappers/generic.py
langswarm/core/wrappers/indexing_mixin.py
langswarm/core/wrappers/logging_mixin.py
langswarm/core/wrappers/memory_mixin.py
langswarm/tests/__init__.py
langswarm/tests/test_factory.py
langswarm/tests/test_integration.py
langswarm/tests/test_registry.py
langswarm/tests/test_wrappers.py
langswarm_core-0.0.18.dist-info/LICENSE
langswarm_core-0.0.18.dist-info/METADATA
langswarm_core-0.0.18.dist-info/WHEEL
langswarm_core-0.0.18.dist-info/top_level.txt
langswarm_core-0.0.18.dist-info/RECORD
