Metadata-Version: 2.2
Name: langswarm-core
Version: 0.0.18
Summary: A core framework for multi-agent LLM ecosystems
Home-page: https://github.com/aekdahl/langswarm-core
Author: Alexander Ekdahl
Author-email: alexander.ekdahl@gmail.com
License: MIT
Classifier: Development Status :: 3 - Alpha
Classifier: Intended Audience :: Developers
Classifier: License :: OSI Approved :: MIT License
Classifier: Programming Language :: Python :: 3.8
Classifier: Programming Language :: Python :: 3.9
Classifier: Programming Language :: Python :: 3.10
Classifier: Programming Language :: Python :: 3.11
Requires-Python: >=3.8
License-File: LICENSE
Requires-Dist: langchain>=0.2.17
Requires-Dist: langchain_community>=0.2.19
Requires-Dist: langchain-openai>=0.1.25
Requires-Dist: tiktoken>=0.7.0
Requires-Dist: llama-index>=0.11.23
Requires-Dist: pyyaml>=6.0.2
Requires-Dist: openai>=0.30.0
Provides-Extra: dev
Requires-Dist: pytest; extra == "dev"
Requires-Dist: black; extra == "dev"
Requires-Dist: flake8; extra == "dev"
Dynamic: author
Dynamic: author-email
Dynamic: classifier
Dynamic: description
Dynamic: description-content-type
Dynamic: home-page
Dynamic: license
Dynamic: provides-extra
Dynamic: requires-dist
Dynamic: requires-python
Dynamic: summary
